fs/__init__.py
fs/_bulk.py
fs/_fscompat.py
fs/_ftp_parse.py
fs/_repr.py
fs/_typing.py
fs/_url_tools.py
fs/_version.py
fs/appfs.py
fs/base.py
fs/compress.py
fs/constants.py
fs/copy.py
fs/enums.py
fs/error_tools.py
fs/errors.py
fs/filesize.py
fs/ftpfs.py
fs/glob.py
fs/info.py
fs/iotools.py
fs/lrucache.py
fs/memoryfs.py
fs/mirror.py
fs/mode.py
fs/mountfs.py
fs/move.py
fs/multifs.py
fs/osfs.py
fs/path.py
fs/permissions.py
fs/subfs.py
fs/tarfs.py
fs/tempfs.py
fs/test.py
fs/time.py
fs/tools.py
fs/tree.py
fs/walk.py
fs/wildcard.py
fs/wrap.py
fs/wrapfs.py
fs/zipfs.py
fs/opener/__init__.py
fs/opener/appfs.py
fs/opener/base.py
fs/opener/errors.py
fs/opener/ftpfs.py
fs/opener/memoryfs.py
fs/opener/osfs.py
fs/opener/parse.py
fs/opener/registry.py
fs/opener/smbfs.py
fs/opener/tarfs.py
fs/opener/tempfs.py
fs/opener/zipfs.py
fs/smbfs/__init__.py
fs/smbfs/file.py
fs/smbfs/smbfs.py
fs/smbfs/utils.py
fs_smb_int-2.4.11.dist-info/LICENSE
fs_smb_int-2.4.11.dist-info/METADATA
fs_smb_int-2.4.11.dist-info/WHEEL
fs_smb_int-2.4.11.dist-info/top_level.txt
fs_smb_int-2.4.11.dist-info/RECORD
