Metadata-Version: 2.1
Name: fs-smb-int
Version: 2.4.11
Summary: fs-smb_int
Home-page: https://github.com/PyFilesystem/pyfilesystem2
Author: Will McGugan
Author-email: will@willmcgugan.com
License: MIT
Project-URL: Bug Reports, https://github.com/PyFilesystem/pyfilesystem2/issues
Project-URL: Documentation, https://pyfilesystem2.readthedocs.io/en/latest/
Project-URL: Wiki, https://www.pyfilesystem.org/
Platform: any
Classifier: Development Status :: 5 - Production/Stable
Classifier: Intended Audience :: Developers
Classifier: License :: OSI Approved :: MIT License
Classifier: Operating System :: OS Independent
Classifier: Programming Language :: Python
Classifier: Programming Language :: Python :: 2.7
Classifier: Programming Language :: Python :: 3.4
Classifier: Programming Language :: Python :: 3.5
Classifier: Programming Language :: Python :: 3.6
Classifier: Programming Language :: Python :: 3.7
Classifier: Programming Language :: Python :: 3.8
Classifier: Programming Language :: Python :: Implementation :: CPython
Classifier: Programming Language :: Python :: Implementation :: PyPy
Classifier: Topic :: System :: Filesystems
Requires-Dist: appdirs (~=1.4.3)
Requires-Dist: pytz
Requires-Dist: setuptools
Requires-Dist: six (~=1.10)
Requires-Dist: backports.os (~=0.1) ; python_version < '3.0'
Requires-Dist: enum34 (~=1.1.6) ; python_version < '3.4'
Requires-Dist: typing (~=3.6) ; python_version < '3.6'
Provides-Extra: scandir_
Requires-Dist: scandir (~=1.5) ; (python_version < '3.5') and extra == 'scandir_'
